evomeai_utils/EConfig.py
evomeai_utils/LogTimer.py
evomeai_utils/__init__.py
evomeai_utils-0.1.5.dist-info/METADATA
evomeai_utils-0.1.5.dist-info/WHEEL
evomeai_utils-0.1.5.dist-info/RECORD
