Metadata-Version: 2.4
Name: evomeai_utils
Version: 0.1.5
Summary: evomeai_utils is a python package for evomeai project.
Project-URL: HomePage, https://gitee.com/footoo/utils
Author-email: flowithwind <flowithwind@gmail.com>
Requires-Python: >=3.8
